{
  "sentences": [
    {
      "text": {
        "content": "Cleo is an orphan kitten.",
        "beginOffset": -1
      },
      "sentiment": {
        "magnitude": 0,
        "score": 0
      }
    },
    {
      "text": {
        "content": "Her mom died two weeks ago.",
        "beginOffset": -1
      },
      "sentiment": {
        "magnitude": 0,
        "score": 0
      }
    },
    {
      "text": {
        "content": "She's an active kitten, love to play and super cute.",
        "beginOffset": -1
      },
      "sentiment": {
        "magnitude": 0.9,
        "score": 0.9
      }
    },
    {
      "text": {
        "content": "Has been dewormed and deflea.",
        "beginOffset": -1
      },
      "sentiment": {
        "magnitude": 0.3,
        "score": 0.3
      }
    },
    {
      "text": {
        "content": "Adopter need to vaccinate and neuter her.",
        "beginOffset": -1
      },
      "sentiment": {
        "magnitude": 0,
        "score": 0
      }
    }
  ],
  "tokens": [],
  "entities": [
    {
      "name": "Cleo",
      "type": "PERSON",
      "metadata": {},
      "salience": 0.54030424,
      "mentions": [
        {
          "text": {
            "content": "Cleo",
            "beginOffset": -1
          },
          "type": "PROPER"
        },
        {
          "text": {
            "content": "kitten",
            "beginOffset": -1
          },
          "type": "COMMON"
        }
      ]
    },
    {
      "name": "kitten",
      "type": "PERSON",
      "metadata": {},
      "salience": 0.43629932,
      "mentions": [
        {
          "text": {
            "content": "mom",
            "beginOffset": -1
          },
          "type": "COMMON"
        },
        {
          "text": {
            "content": "kitten",
            "beginOffset": -1
          },
          "type": "COMMON"
        }
      ]
    },
    {
      "name": "Adopter",
      "type": "PERSON",
      "metadata": {},
      "salience": 0.016207118,
      "mentions": [
        {
          "text": {
            "content": "Adopter",
            "beginOffset": -1
          },
          "type": "COMMON"
        }
      ]
    },
    {
      "name": "deflea",
      "type": "OTHER",
      "metadata": {},
      "salience": 0.0071892873,
      "mentions": [
        {
          "text": {
            "content": "deflea",
            "beginOffset": -1
          },
          "type": "COMMON"
        }
      ]
    }
  ],
  "documentSentiment": {
    "magnitude": 1.3,
    "score": 0.2
  },
  "language": "en",
  "categories": []
}
