{
  "sentences": [
    {
      "text": {
        "content": "Shih Tzu Found on 2nd Nov night around Pavilion Kuala Lumpur area.",
        "beginOffset": -1
      },
      "sentiment": {
        "magnitude": 0.1,
        "score": 0.1
      }
    },
    {
      "text": {
        "content": "Dog was found wandering around road side during heavy rain.",
        "beginOffset": -1
      },
      "sentiment": {
        "magnitude": 0.1,
        "score": 0.1
      }
    },
    {
      "text": {
        "content": "(The dog is already adopted by a family)",
        "beginOffset": -1
      },
      "sentiment": {
        "magnitude": 0.1,
        "score": 0.1
      }
    }
  ],
  "tokens": [],
  "entities": [
    {
      "name": "Shih Tzu",
      "type": "ORGANIZATION",
      "metadata": {
        "mid": "/m/01s7fj",
        "wikipedia_url": "https://en.wikipedia.org/wiki/Shih_Tzu"
      },
      "salience": 0.47862607,
      "mentions": [
        {
          "text": {
            "content": "Shih Tzu",
            "beginOffset": -1
          },
          "type": "PROPER"
        }
      ]
    },
    {
      "name": "area",
      "type": "LOCATION",
      "metadata": {},
      "salience": 0.16317298,
      "mentions": [
        {
          "text": {
            "content": "area",
            "beginOffset": -1
          },
          "type": "COMMON"
        }
      ]
    },
    {
      "name": "Pavilion Kuala Lumpur",
      "type": "LOCATION",
      "metadata": {
        "wikipedia_url": "https://en.wikipedia.org/wiki/Pavilion_Kuala_Lumpur",
        "mid": "/m/02rsrts"
      },
      "salience": 0.098651424,
      "mentions": [
        {
          "text": {
            "content": "Pavilion Kuala Lumpur",
            "beginOffset": -1
          },
          "type": "PROPER"
        }
      ]
    },
    {
      "name": "road side",
      "type": "OTHER",
      "metadata": {},
      "salience": 0.07497836,
      "mentions": [
        {
          "text": {
            "content": "road side",
            "beginOffset": -1
          },
          "type": "COMMON"
        }
      ]
    },
    {
      "name": "dog",
      "type": "OTHER",
      "metadata": {},
      "salience": 0.06423383,
      "mentions": [
        {
          "text": {
            "content": "dog",
            "beginOffset": -1
          },
          "type": "COMMON"
        }
      ]
    },
    {
      "name": "Dog",
      "type": "PERSON",
      "metadata": {
        "mid": "/m/0bt9lr",
        "wikipedia_url": "https://en.wikipedia.org/wiki/Dog"
      },
      "salience": 0.055353895,
      "mentions": [
        {
          "text": {
            "content": "Dog",
            "beginOffset": -1
          },
          "type": "PROPER"
        }
      ]
    },
    {
      "name": "family",
      "type": "PERSON",
      "metadata": {},
      "salience": 0.039805077,
      "mentions": [
        {
          "text": {
            "content": "family",
            "beginOffset": -1
          },
          "type": "COMMON"
        }
      ]
    },
    {
      "name": "rain",
      "type": "OTHER",
      "metadata": {},
      "salience": 0.025178354,
      "mentions": [
        {
          "text": {
            "content": "rain",
            "beginOffset": -1
          },
          "type": "COMMON"
        }
      ]
    }
  ],
  "documentSentiment": {
    "magnitude": 0.4,
    "score": 0.1
  },
  "language": "en",
  "categories": []
}
