{
  "sentences": [
    {
      "text": {
        "content": "I picked Zoey up from a drain.",
        "beginOffset": -1
      },
      "sentiment": {
        "magnitude": 0.2,
        "score": -0.2
      }
    },
    {
      "text": {
        "content": "She was entangled in plants and twigs.",
        "beginOffset": -1
      },
      "sentiment": {
        "magnitude": 0.1,
        "score": 0.1
      }
    },
    {
      "text": {
        "content": "She probably fell in as she could not see.",
        "beginOffset": -1
      },
      "sentiment": {
        "magnitude": 0.2,
        "score": -0.2
      }
    },
    {
      "text": {
        "content": "she had a severe eye infection and her eyes were sealed shut.",
        "beginOffset": -1
      },
      "sentiment": {
        "magnitude": 0.3,
        "score": -0.3
      }
    },
    {
      "text": {
        "content": "also from the fall she sprained her back legs and was walking on 3 legs.",
        "beginOffset": -1
      },
      "sentiment": {
        "magnitude": 0,
        "score": 0
      }
    },
    {
      "text": {
        "content": "after some intense tlc, a trip to the vet, zoey is now a healthy, very active, extremely manja girl with a big appetite.",
        "beginOffset": -1
      },
      "sentiment": {
        "magnitude": 0.8,
        "score": 0.8
      }
    },
    {
      "text": {
        "content": "Would be very grateful if you could give this girl whose been through so much at such a young age a forever home.",
        "beginOffset": -1
      },
      "sentiment": {
        "magnitude": 0.3,
        "score": 0.3
      }
    }
  ],
  "tokens": [],
  "entities": [
    {
      "name": "Zoey",
      "type": "PERSON",
      "metadata": {},
      "salience": 0.7945742,
      "mentions": [
        {
          "text": {
            "content": "Zoey",
            "beginOffset": -1
          },
          "type": "PROPER"
        },
        {
          "text": {
            "content": "zoey",
            "beginOffset": -1
          },
          "type": "PROPER"
        },
        {
          "text": {
            "content": "girl",
            "beginOffset": -1
          },
          "type": "COMMON"
        },
        {
          "text": {
            "content": "girl",
            "beginOffset": -1
          },
          "type": "COMMON"
        }
      ]
    },
    {
      "name": "drain",
      "type": "OTHER",
      "metadata": {},
      "salience": 0.07320002,
      "mentions": [
        {
          "text": {
            "content": "drain",
            "beginOffset": -1
          },
          "type": "COMMON"
        }
      ]
    },
    {
      "name": "plants",
      "type": "LOCATION",
      "metadata": {},
      "salience": 0.036262088,
      "mentions": [
        {
          "text": {
            "content": "plants",
            "beginOffset": -1
          },
          "type": "COMMON"
        }
      ]
    },
    {
      "name": "twigs",
      "type": "OTHER",
      "metadata": {},
      "salience": 0.013970902,
      "mentions": [
        {
          "text": {
            "content": "twigs",
            "beginOffset": -1
          },
          "type": "COMMON"
        }
      ]
    },
    {
      "name": "legs",
      "type": "OTHER",
      "metadata": {},
      "salience": 0.010766464,
      "mentions": [
        {
          "text": {
            "content": "legs",
            "beginOffset": -1
          },
          "type": "COMMON"
        }
      ]
    },
    {
      "name": "legs",
      "type": "OTHER",
      "metadata": {},
      "salience": 0.010766464,
      "mentions": [
        {
          "text": {
            "content": "legs",
            "beginOffset": -1
          },
          "type": "COMMON"
        }
      ]
    },
    {
      "name": "eye infection",
      "type": "OTHER",
      "metadata": {},
      "salience": 0.009376423,
      "mentions": [
        {
          "text": {
            "content": "eye infection",
            "beginOffset": -1
          },
          "type": "COMMON"
        }
      ]
    },
    {
      "name": "eyes",
      "type": "OTHER",
      "metadata": {},
      "salience": 0.009376423,
      "mentions": [
        {
          "text": {
            "content": "eyes",
            "beginOffset": -1
          },
          "type": "COMMON"
        }
      ]
    },
    {
      "name": "tlc",
      "type": "OTHER",
      "metadata": {},
      "salience": 0.008670264,
      "mentions": [
        {
          "text": {
            "content": "tlc",
            "beginOffset": -1
          },
          "type": "COMMON"
        }
      ]
    },
    {
      "name": "trip",
      "type": "EVENT",
      "metadata": {},
      "salience": 0.008670264,
      "mentions": [
        {
          "text": {
            "content": "trip",
            "beginOffset": -1
          },
          "type": "COMMON"
        }
      ]
    },
    {
      "name": "vet",
      "type": "PERSON",
      "metadata": {},
      "salience": 0.008670264,
      "mentions": [
        {
          "text": {
            "content": "vet",
            "beginOffset": -1
          },
          "type": "COMMON"
        }
      ]
    },
    {
      "name": "appetite",
      "type": "OTHER",
      "metadata": {},
      "salience": 0.006543031,
      "mentions": [
        {
          "text": {
            "content": "appetite",
            "beginOffset": -1
          },
          "type": "COMMON"
        }
      ]
    },
    {
      "name": "age",
      "type": "OTHER",
      "metadata": {},
      "salience": 0.0045765894,
      "mentions": [
        {
          "text": {
            "content": "age",
            "beginOffset": -1
          },
          "type": "COMMON"
        }
      ]
    },
    {
      "name": "home",
      "type": "LOCATION",
      "metadata": {},
      "salience": 0.0045765894,
      "mentions": [
        {
          "text": {
            "content": "home",
            "beginOffset": -1
          },
          "type": "COMMON"
        }
      ]
    }
  ],
  "documentSentiment": {
    "magnitude": 2.2,
    "score": 0
  },
  "language": "en",
  "categories": []
}
