{
  "sentences": [
    {
      "text": {
        "content": "Teddy is like a little fluff ball that makes him look all puffy!",
        "beginOffset": -1
      },
      "sentiment": {
        "magnitude": 0.2,
        "score": 0.2
      }
    },
    {
      "text": {
        "content": "He's the biggest among his brothers but is actually a sweet little guy.",
        "beginOffset": -1
      },
      "sentiment": {
        "magnitude": 0.7,
        "score": 0.7
      }
    },
    {
      "text": {
        "content": "Teddy is rescued from the street along with his mommy and two other brothers - Sammy &amp; Little Champ.",
        "beginOffset": -1
      },
      "sentiment": {
        "magnitude": 0,
        "score": 0
      }
    },
    {
      "text": {
        "content": "He is around 7 weeks old.",
        "beginOffset": -1
      },
      "sentiment": {
        "magnitude": 0,
        "score": 0
      }
    },
    {
      "text": {
        "content": "(26 March ) Please call if you can give him a loving home.",
        "beginOffset": -1
      },
      "sentiment": {
        "magnitude": 0.6,
        "score": 0.6
      }
    },
    {
      "text": {
        "content": "New owner must promise to have him neutered at 6 month old.",
        "beginOffset": -1
      },
      "sentiment": {
        "magnitude": 0.1,
        "score": 0.1
      }
    },
    {
      "text": {
        "content": "I've already dewormed him and had him treated for fleas and ear mites.",
        "beginOffset": -1
      },
      "sentiment": {
        "magnitude": 0.9,
        "score": -0.9
      }
    },
    {
      "text": {
        "content": "It'll be great if you can adopt his sister - Little Champ too.",
        "beginOffset": -1
      },
      "sentiment": {
        "magnitude": 0.7,
        "score": 0.7
      }
    },
    {
      "text": {
        "content": "They play so well together and can keep each other company. =)",
        "beginOffset": -1
      },
      "sentiment": {
        "magnitude": 0.8,
        "score": 0.8
      }
    }
  ],
  "tokens": [],
  "entities": [
    {
      "name": "Teddy",
      "type": "PERSON",
      "metadata": {},
      "salience": 0.6757066,
      "mentions": [
        {
          "text": {
            "content": "Teddy",
            "beginOffset": -1
          },
          "type": "PROPER"
        },
        {
          "text": {
            "content": "Teddy",
            "beginOffset": -1
          },
          "type": "PROPER"
        }
      ]
    },
    {
      "name": "fluff ball",
      "type": "OTHER",
      "metadata": {},
      "salience": 0.19293408,
      "mentions": [
        {
          "text": {
            "content": "fluff ball",
            "beginOffset": -1
          },
          "type": "COMMON"
        }
      ]
    },
    {
      "name": "guy",
      "type": "PERSON",
      "metadata": {},
      "salience": 0.019708607,
      "mentions": [
        {
          "text": {
            "content": "guy",
            "beginOffset": -1
          },
          "type": "COMMON"
        }
      ]
    },
    {
      "name": "brothers",
      "type": "PERSON",
      "metadata": {},
      "salience": 0.0175656,
      "mentions": [
        {
          "text": {
            "content": "brothers",
            "beginOffset": -1
          },
          "type": "COMMON"
        }
      ]
    },
    {
      "name": "biggest",
      "type": "OTHER",
      "metadata": {},
      "salience": 0.015447642,
      "mentions": [
        {
          "text": {
            "content": "biggest",
            "beginOffset": -1
          },
          "type": "COMMON"
        }
      ]
    },
    {
      "name": "owner",
      "type": "PERSON",
      "metadata": {},
      "salience": 0.012721282,
      "mentions": [
        {
          "text": {
            "content": "owner",
            "beginOffset": -1
          },
          "type": "COMMON"
        }
      ]
    },
    {
      "name": "brothers",
      "type": "PERSON",
      "metadata": {},
      "salience": 0.01182815,
      "mentions": [
        {
          "text": {
            "content": "brothers",
            "beginOffset": -1
          },
          "type": "COMMON"
        }
      ]
    },
    {
      "name": "Sammy & Little Champ",
      "type": "PERSON",
      "metadata": {},
      "salience": 0.011012416,
      "mentions": [
        {
          "text": {
            "content": "Sammy &amp; Little Champ",
            "beginOffset": -1
          },
          "type": "PROPER"
        },
        {
          "text": {
            "content": "Little Champ",
            "beginOffset": -1
          },
          "type": "PROPER"
        }
      ]
    },
    {
      "name": "street",
      "type": "LOCATION",
      "metadata": {},
      "salience": 0.010397315,
      "mentions": [
        {
          "text": {
            "content": "street",
            "beginOffset": -1
          },
          "type": "COMMON"
        }
      ]
    },
    {
      "name": "mommy",
      "type": "OTHER",
      "metadata": {},
      "salience": 0.010397315,
      "mentions": [
        {
          "text": {
            "content": "mommy",
            "beginOffset": -1
          },
          "type": "COMMON"
        }
      ]
    },
    {
      "name": "home",
      "type": "LOCATION",
      "metadata": {},
      "salience": 0.00733256,
      "mentions": [
        {
          "text": {
            "content": "home",
            "beginOffset": -1
          },
          "type": "COMMON"
        }
      ]
    },
    {
      "name": "ear mites",
      "type": "OTHER",
      "metadata": {},
      "salience": 0.0072133876,
      "mentions": [
        {
          "text": {
            "content": "ear mites",
            "beginOffset": -1
          },
          "type": "COMMON"
        }
      ]
    },
    {
      "name": "company.",
      "type": "ORGANIZATION",
      "metadata": {},
      "salience": 0.004566636,
      "mentions": [
        {
          "text": {
            "content": "company.",
            "beginOffset": -1
          },
          "type": "COMMON"
        }
      ]
    },
    {
      "name": "fleas",
      "type": "OTHER",
      "metadata": {},
      "salience": 0.0031684055,
      "mentions": [
        {
          "text": {
            "content": "fleas",
            "beginOffset": -1
          },
          "type": "COMMON"
        }
      ]
    }
  ],
  "documentSentiment": {
    "magnitude": 4.4,
    "score": 0.2
  },
  "language": "en",
  "categories": []
}
