{
  "sentences": [
    {
      "text": {
        "content": "Bella is looking for urgent home so I can rescue their remaining siblings from the construction site.",
        "beginOffset": -1
      },
      "sentiment": {
        "magnitude": 0.8,
        "score": 0.8
      }
    },
    {
      "text": {
        "content": "One of the worker who initially refused to hand over puppies when I beg them to help me to pass me the puppies so I can try to rehome, rather than stuck at the construction site, were telling me that the boss that owns the lorries doesnt want anymore puppies be there anymore.",
        "beginOffset": -1
      },
      "sentiment": {
        "magnitude": 0.2,
        "score": -0.2
      }
    },
    {
      "text": {
        "content": "He might throw them away.",
        "beginOffset": -1
      },
      "sentiment": {
        "magnitude": 0.2,
        "score": -0.2
      }
    },
    {
      "text": {
        "content": "Pls adopt &amp; save lifes today!",
        "beginOffset": -1
      },
      "sentiment": {
        "magnitude": 0.3,
        "score": 0.3
      }
    },
    {
      "text": {
        "content": "Location KL",
        "beginOffset": -1
      },
      "sentiment": {
        "magnitude": 0.1,
        "score": 0.1
      }
    }
  ],
  "tokens": [],
  "entities": [
    {
      "name": "One",
      "type": "OTHER",
      "metadata": {},
      "salience": 0.19693227,
      "mentions": [
        {
          "text": {
            "content": "One",
            "beginOffset": -1
          },
          "type": "COMMON"
        }
      ]
    },
    {
      "name": "home",
      "type": "LOCATION",
      "metadata": {},
      "salience": 0.18914191,
      "mentions": [
        {
          "text": {
            "content": "home",
            "beginOffset": -1
          },
          "type": "COMMON"
        }
      ]
    },
    {
      "name": "Bella",
      "type": "PERSON",
      "metadata": {},
      "salience": 0.111955464,
      "mentions": [
        {
          "text": {
            "content": "Bella",
            "beginOffset": -1
          },
          "type": "PROPER"
        }
      ]
    },
    {
      "name": "worker",
      "type": "PERSON",
      "metadata": {},
      "salience": 0.090606675,
      "mentions": [
        {
          "text": {
            "content": "worker",
            "beginOffset": -1
          },
          "type": "COMMON"
        }
      ]
    },
    {
      "name": "construction site",
      "type": "LOCATION",
      "metadata": {},
      "salience": 0.084374435,
      "mentions": [
        {
          "text": {
            "content": "construction site",
            "beginOffset": -1
          },
          "type": "COMMON"
        }
      ]
    },
    {
      "name": "siblings",
      "type": "PERSON",
      "metadata": {},
      "salience": 0.074350245,
      "mentions": [
        {
          "text": {
            "content": "siblings",
            "beginOffset": -1
          },
          "type": "COMMON"
        }
      ]
    },
    {
      "name": "puppies",
      "type": "OTHER",
      "metadata": {},
      "salience": 0.071303755,
      "mentions": [
        {
          "text": {
            "content": "puppies",
            "beginOffset": -1
          },
          "type": "COMMON"
        }
      ]
    },
    {
      "name": "boss",
      "type": "PERSON",
      "metadata": {},
      "salience": 0.064737566,
      "mentions": [
        {
          "text": {
            "content": "boss",
            "beginOffset": -1
          },
          "type": "COMMON"
        }
      ]
    },
    {
      "name": "puppies",
      "type": "OTHER",
      "metadata": {},
      "salience": 0.033158466,
      "mentions": [
        {
          "text": {
            "content": "puppies",
            "beginOffset": -1
          },
          "type": "COMMON"
        }
      ]
    },
    {
      "name": "puppies",
      "type": "OTHER",
      "metadata": {},
      "salience": 0.026298974,
      "mentions": [
        {
          "text": {
            "content": "puppies",
            "beginOffset": -1
          },
          "type": "COMMON"
        }
      ]
    },
    {
      "name": "construction site",
      "type": "LOCATION",
      "metadata": {},
      "salience": 0.025827982,
      "mentions": [
        {
          "text": {
            "content": "construction site",
            "beginOffset": -1
          },
          "type": "COMMON"
        }
      ]
    },
    {
      "name": "lifes",
      "type": "OTHER",
      "metadata": {},
      "salience": 0.011906953,
      "mentions": [
        {
          "text": {
            "content": "lifes",
            "beginOffset": -1
          },
          "type": "COMMON"
        }
      ]
    },
    {
      "name": "Location KL",
      "type": "OTHER",
      "metadata": {},
      "salience": 0.011874396,
      "mentions": [
        {
          "text": {
            "content": "Location KL",
            "beginOffset": -1
          },
          "type": "COMMON"
        }
      ]
    },
    {
      "name": "lorries",
      "type": "CONSUMER_GOOD",
      "metadata": {},
      "salience": 0.0075309067,
      "mentions": [
        {
          "text": {
            "content": "lorries",
            "beginOffset": -1
          },
          "type": "COMMON"
        }
      ]
    }
  ],
  "documentSentiment": {
    "magnitude": 1.8,
    "score": 0.1
  },
  "language": "en",
  "categories": []
}
