{
  "sentences": [
    {
      "text": {
        "content": "Pooh Pooh from Penang and now around 3 years old and look for new owner who are pets lover and treat her nicely.",
        "beginOffset": -1
      },
      "sentiment": {
        "magnitude": 0.9,
        "score": 0.9
      }
    },
    {
      "text": {
        "content": "For those interested may contact (Mr Ooi) for futher discussion.",
        "beginOffset": -1
      },
      "sentiment": {
        "magnitude": 0,
        "score": 0
      }
    }
  ],
  "tokens": [],
  "entities": [
    {
      "name": "owner",
      "type": "PERSON",
      "metadata": {},
      "salience": 0.50445324,
      "mentions": [
        {
          "text": {
            "content": "owner",
            "beginOffset": -1
          },
          "type": "COMMON"
        },
        {
          "text": {
            "content": "lover",
            "beginOffset": -1
          },
          "type": "COMMON"
        }
      ]
    },
    {
      "name": "Pooh",
      "type": "OTHER",
      "metadata": {},
      "salience": 0.21548875,
      "mentions": [
        {
          "text": {
            "content": "Pooh",
            "beginOffset": -1
          },
          "type": "PROPER"
        }
      ]
    },
    {
      "name": "Penang",
      "type": "LOCATION",
      "metadata": {
        "wikipedia_url": "https://en.wikipedia.org/wiki/Penang",
        "mid": "/m/0g6xq"
      },
      "salience": 0.19185239,
      "mentions": [
        {
          "text": {
            "content": "Penang",
            "beginOffset": -1
          },
          "type": "PROPER"
        }
      ]
    },
    {
      "name": "Ooi",
      "type": "PERSON",
      "metadata": {},
      "salience": 0.06688686,
      "mentions": [
        {
          "text": {
            "content": "Ooi",
            "beginOffset": -1
          },
          "type": "PROPER"
        },
        {
          "text": {
            "content": "Mr",
            "beginOffset": -1
          },
          "type": "COMMON"
        }
      ]
    },
    {
      "name": "discussion",
      "type": "OTHER",
      "metadata": {},
      "salience": 0.021318791,
      "mentions": [
        {
          "text": {
            "content": "discussion",
            "beginOffset": -1
          },
          "type": "COMMON"
        }
      ]
    }
  ],
  "documentSentiment": {
    "magnitude": 1,
    "score": 0.5
  },
  "language": "en",
  "categories": []
}
