{
  "sentences": [
    {
      "text": {
        "content": "Actually , i saved this puppy from dog pund DBKL.",
        "beginOffset": -1
      },
      "sentiment": {
        "magnitude": 0.4,
        "score": 0.4
      }
    },
    {
      "text": {
        "content": "used to feed them in the field opposite to my house.",
        "beginOffset": -1
      },
      "sentiment": {
        "magnitude": 0,
        "score": 0
      }
    },
    {
      "text": {
        "content": "Coz 1 of the mother dog's leg was broken/injured.",
        "beginOffset": -1
      },
      "sentiment": {
        "magnitude": 0.7,
        "score": -0.7
      }
    },
    {
      "text": {
        "content": "Some1 reported to DBKL, so when i save the 3 puppies from DBKL, i sent them to vet from observation.",
        "beginOffset": -1
      },
      "sentiment": {
        "magnitude": 0.4,
        "score": -0.4
      }
    },
    {
      "text": {
        "content": "1 of them cant make it and passed awasy in last week.",
        "beginOffset": -1
      },
      "sentiment": {
        "magnitude": 0.3,
        "score": -0.3
      }
    },
    {
      "text": {
        "content": "&amp; 2 were survived.",
        "beginOffset": -1
      },
      "sentiment": {
        "magnitude": 0.1,
        "score": 0.1
      }
    },
    {
      "text": {
        "content": "Will vacinate them in these 2 weeks.",
        "beginOffset": -1
      },
      "sentiment": {
        "magnitude": 0,
        "score": 0
      }
    },
    {
      "text": {
        "content": "Hope to get adopter for them coz my house is not allowed to have a pet.",
        "beginOffset": -1
      },
      "sentiment": {
        "magnitude": 0,
        "score": 0
      }
    },
    {
      "text": {
        "content": "she is now actually in dr Lee's veternirary in kuchai lama, who ever interested adopting her , u can go there to visit her..() thank you.",
        "beginOffset": -1
      },
      "sentiment": {
        "magnitude": 0.2,
        "score": 0.2
      }
    }
  ],
  "tokens": [],
  "entities": [
    {
      "name": "DBKL",
      "type": "ORGANIZATION",
      "metadata": {
        "wikipedia_url": "https://en.wikipedia.org/wiki/Kuala_Lumpur_City_Hall",
        "mid": "/m/0cnp39"
      },
      "salience": 0.32797158,
      "mentions": [
        {
          "text": {
            "content": "dog pund DBKL",
            "beginOffset": -1
          },
          "type": "COMMON"
        },
        {
          "text": {
            "content": "DBKL",
            "beginOffset": -1
          },
          "type": "PROPER"
        },
        {
          "text": {
            "content": "DBKL",
            "beginOffset": -1
          },
          "type": "PROPER"
        }
      ]
    },
    {
      "name": "puppy",
      "type": "OTHER",
      "metadata": {},
      "salience": 0.17645982,
      "mentions": [
        {
          "text": {
            "content": "puppy",
            "beginOffset": -1
          },
          "type": "COMMON"
        }
      ]
    },
    {
      "name": "house",
      "type": "LOCATION",
      "metadata": {},
      "salience": 0.15272756,
      "mentions": [
        {
          "text": {
            "content": "house",
            "beginOffset": -1
          },
          "type": "COMMON"
        },
        {
          "text": {
            "content": "house",
            "beginOffset": -1
          },
          "type": "COMMON"
        }
      ]
    },
    {
      "name": "Some1",
      "type": "ORGANIZATION",
      "metadata": {},
      "salience": 0.11201349,
      "mentions": [
        {
          "text": {
            "content": "Some1",
            "beginOffset": -1
          },
          "type": "PROPER"
        }
      ]
    },
    {
      "name": "mother dog",
      "type": "PERSON",
      "metadata": {},
      "salience": 0.033194758,
      "mentions": [
        {
          "text": {
            "content": "mother dog",
            "beginOffset": -1
          },
          "type": "COMMON"
        }
      ]
    },
    {
      "name": "Lee",
      "type": "PERSON",
      "metadata": {},
      "salience": 0.030529765,
      "mentions": [
        {
          "text": {
            "content": "Lee",
            "beginOffset": -1
          },
          "type": "PROPER"
        },
        {
          "text": {
            "content": "dr",
            "beginOffset": -1
          },
          "type": "COMMON"
        }
      ]
    },
    {
      "name": "field",
      "type": "LOCATION",
      "metadata": {},
      "salience": 0.029331308,
      "mentions": [
        {
          "text": {
            "content": "field",
            "beginOffset": -1
          },
          "type": "COMMON"
        }
      ]
    },
    {
      "name": "leg",
      "type": "OTHER",
      "metadata": {},
      "salience": 0.029186409,
      "mentions": [
        {
          "text": {
            "content": "leg",
            "beginOffset": -1
          },
          "type": "COMMON"
        }
      ]
    },
    {
      "name": "puppies",
      "type": "OTHER",
      "metadata": {},
      "salience": 0.022372315,
      "mentions": [
        {
          "text": {
            "content": "puppies",
            "beginOffset": -1
          },
          "type": "COMMON"
        }
      ]
    },
    {
      "name": "awasy",
      "type": "OTHER",
      "metadata": {},
      "salience": 0.021364633,
      "mentions": [
        {
          "text": {
            "content": "awasy",
            "beginOffset": -1
          },
          "type": "COMMON"
        }
      ]
    },
    {
      "name": "observation",
      "type": "OTHER",
      "metadata": {},
      "salience": 0.019905608,
      "mentions": [
        {
          "text": {
            "content": "observation",
            "beginOffset": -1
          },
          "type": "COMMON"
        }
      ]
    },
    {
      "name": "Coz 1",
      "type": "ORGANIZATION",
      "metadata": {},
      "salience": 0.017300365,
      "mentions": [
        {
          "text": {
            "content": "Coz 1",
            "beginOffset": -1
          },
          "type": "PROPER"
        }
      ]
    },
    {
      "name": "veternirary",
      "type": "OTHER",
      "metadata": {},
      "salience": 0.013643854,
      "mentions": [
        {
          "text": {
            "content": "veternirary",
            "beginOffset": -1
          },
          "type": "COMMON"
        }
      ]
    },
    {
      "name": "kuchai lama",
      "type": "LOCATION",
      "metadata": {
        "mid": "/m/0d_d00",
        "wikipedia_url": "https://en.wikipedia.org/wiki/Kuchai_Lama"
      },
      "salience": 0.00807255,
      "mentions": [
        {
          "text": {
            "content": "kuchai lama",
            "beginOffset": -1
          },
          "type": "PROPER"
        }
      ]
    },
    {
      "name": "pet",
      "type": "OTHER",
      "metadata": {},
      "salience": 0.0059259916,
      "mentions": [
        {
          "text": {
            "content": "pet",
            "beginOffset": -1
          },
          "type": "COMMON"
        }
      ]
    }
  ],
  "documentSentiment": {
    "magnitude": 2.6,
    "score": -0.1
  },
  "language": "en",
  "categories": []
}
