{
  "sentences": [
    {
      "text": {
        "content": "Hi all gohgoh and jehjeh, my name is Bunny and I was born and grown up at a factory area about 10months ago.",
        "beginOffset": -1
      },
      "sentiment": {
        "magnitude": 0.4,
        "score": 0.4
      }
    },
    {
      "text": {
        "content": "The owner of the factory has been feeding me and my mommy in the past however due to some unforeseen circumstances, the owner is closing down his business.",
        "beginOffset": -1
      },
      "sentiment": {
        "magnitude": 0.3,
        "score": -0.3
      }
    },
    {
      "text": {
        "content": "The owner daughter brought me and my mommy for spayed and found a forever home for my mommy and a temporary foster home for me.",
        "beginOffset": -1
      },
      "sentiment": {
        "magnitude": 0.3,
        "score": 0.3
      }
    },
    {
      "text": {
        "content": "I am an active and alert dog, my rescue sister said I am a very good guard dog (oh, not to mention I'm super manja!!).",
        "beginOffset": -1
      },
      "sentiment": {
        "magnitude": 0.8,
        "score": 0.8
      }
    },
    {
      "text": {
        "content": "I loves being around with my human family and loves my foster sisters (we are best buddy!).",
        "beginOffset": -1
      },
      "sentiment": {
        "magnitude": 0.9,
        "score": 0.9
      }
    },
    {
      "text": {
        "content": "As much as I am healthy mentally and physically, i do have some skin rashes and red dots on my body.",
        "beginOffset": -1
      },
      "sentiment": {
        "magnitude": 0.2,
        "score": 0.2
      }
    },
    {
      "text": {
        "content": "I will need medication for this condition until some bad bacterias in my body is fully killed.",
        "beginOffset": -1
      },
      "sentiment": {
        "magnitude": 0.3,
        "score": -0.3
      }
    },
    {
      "text": {
        "content": "Please give me a forever home and I promise, i will surely repay you with all my loves *woof*",
        "beginOffset": -1
      },
      "sentiment": {
        "magnitude": 0.8,
        "score": 0.8
      }
    }
  ],
  "tokens": [],
  "entities": [
    {
      "name": "dog",
      "type": "OTHER",
      "metadata": {},
      "salience": 0.5111428,
      "mentions": [
        {
          "text": {
            "content": "dog",
            "beginOffset": -1
          },
          "type": "COMMON"
        }
      ]
    },
    {
      "name": "guard dog",
      "type": "PERSON",
      "metadata": {},
      "salience": 0.13186419,
      "mentions": [
        {
          "text": {
            "content": "guard dog",
            "beginOffset": -1
          },
          "type": "COMMON"
        }
      ]
    },
    {
      "name": "mommy",
      "type": "OTHER",
      "metadata": {},
      "salience": 0.05185704,
      "mentions": [
        {
          "text": {
            "content": "mommy",
            "beginOffset": -1
          },
          "type": "COMMON"
        },
        {
          "text": {
            "content": "mommy",
            "beginOffset": -1
          },
          "type": "COMMON"
        },
        {
          "text": {
            "content": "mommy",
            "beginOffset": -1
          },
          "type": "COMMON"
        }
      ]
    },
    {
      "name": "name",
      "type": "OTHER",
      "metadata": {},
      "salience": 0.044517227,
      "mentions": [
        {
          "text": {
            "content": "name",
            "beginOffset": -1
          },
          "type": "COMMON"
        }
      ]
    },
    {
      "name": "gohgoh",
      "type": "OTHER",
      "metadata": {},
      "salience": 0.037214737,
      "mentions": [
        {
          "text": {
            "content": "gohgoh",
            "beginOffset": -1
          },
          "type": "COMMON"
        }
      ]
    },
    {
      "name": "jehjeh",
      "type": "OTHER",
      "metadata": {},
      "salience": 0.037214737,
      "mentions": [
        {
          "text": {
            "content": "jehjeh",
            "beginOffset": -1
          },
          "type": "COMMON"
        }
      ]
    },
    {
      "name": "factory area",
      "type": "LOCATION",
      "metadata": {},
      "salience": 0.037214737,
      "mentions": [
        {
          "text": {
            "content": "factory area",
            "beginOffset": -1
          },
          "type": "COMMON"
        }
      ]
    },
    {
      "name": "owner",
      "type": "PERSON",
      "metadata": {},
      "salience": 0.030902589,
      "mentions": [
        {
          "text": {
            "content": "owner",
            "beginOffset": -1
          },
          "type": "COMMON"
        }
      ]
    },
    {
      "name": "Bunny",
      "type": "PERSON",
      "metadata": {},
      "salience": 0.02831561,
      "mentions": [
        {
          "text": {
            "content": "Bunny",
            "beginOffset": -1
          },
          "type": "PROPER"
        }
      ]
    },
    {
      "name": "body",
      "type": "OTHER",
      "metadata": {},
      "salience": 0.012381556,
      "mentions": [
        {
          "text": {
            "content": "body",
            "beginOffset": -1
          },
          "type": "COMMON"
        },
        {
          "text": {
            "content": "body",
            "beginOffset": -1
          },
          "type": "COMMON"
        }
      ]
    },
    {
      "name": "owner",
      "type": "PERSON",
      "metadata": {},
      "salience": 0.008601272,
      "mentions": [
        {
          "text": {
            "content": "owner",
            "beginOffset": -1
          },
          "type": "COMMON"
        }
      ]
    },
    {
      "name": "factory",
      "type": "LOCATION",
      "metadata": {},
      "salience": 0.007848615,
      "mentions": [
        {
          "text": {
            "content": "factory",
            "beginOffset": -1
          },
          "type": "COMMON"
        }
      ]
    },
    {
      "name": "circumstances",
      "type": "OTHER",
      "metadata": {},
      "salience": 0.0068977107,
      "mentions": [
        {
          "text": {
            "content": "circumstances",
            "beginOffset": -1
          },
          "type": "COMMON"
        }
      ]
    },
    {
      "name": "home",
      "type": "LOCATION",
      "metadata": {},
      "salience": 0.0052755675,
      "mentions": [
        {
          "text": {
            "content": "home",
            "beginOffset": -1
          },
          "type": "COMMON"
        }
      ]
    },
    {
      "name": "rescue sister",
      "type": "PERSON",
      "metadata": {},
      "salience": 0.0049441224,
      "mentions": [
        {
          "text": {
            "content": "rescue sister",
            "beginOffset": -1
          },
          "type": "COMMON"
        }
      ]
    },
    {
      "name": "home",
      "type": "LOCATION",
      "metadata": {},
      "salience": 0.0046925726,
      "mentions": [
        {
          "text": {
            "content": "home",
            "beginOffset": -1
          },
          "type": "COMMON"
        }
      ]
    },
    {
      "name": "manja",
      "type": "PERSON",
      "metadata": {},
      "salience": 0.0042909593,
      "mentions": [
        {
          "text": {
            "content": "manja",
            "beginOffset": -1
          },
          "type": "COMMON"
        }
      ]
    },
    {
      "name": "human family",
      "type": "PERSON",
      "metadata": {},
      "salience": 0.004279218,
      "mentions": [
        {
          "text": {
            "content": "human family",
            "beginOffset": -1
          },
          "type": "COMMON"
        }
      ]
    },
    {
      "name": "business",
      "type": "OTHER",
      "metadata": {},
      "salience": 0.0035121269,
      "mentions": [
        {
          "text": {
            "content": "business",
            "beginOffset": -1
          },
          "type": "COMMON"
        }
      ]
    },
    {
      "name": "dots",
      "type": "OTHER",
      "metadata": {},
      "salience": 0.0032187696,
      "mentions": [
        {
          "text": {
            "content": "dots",
            "beginOffset": -1
          },
          "type": "COMMON"
        }
      ]
    },
    {
      "name": "condition",
      "type": "OTHER",
      "metadata": {},
      "salience": 0.003212678,
      "mentions": [
        {
          "text": {
            "content": "condition",
            "beginOffset": -1
          },
          "type": "COMMON"
        }
      ]
    },
    {
      "name": "bacterias",
      "type": "OTHER",
      "metadata": {},
      "salience": 0.003212678,
      "mentions": [
        {
          "text": {
            "content": "bacterias",
            "beginOffset": -1
          },
          "type": "COMMON"
        }
      ]
    },
    {
      "name": "skin rashes",
      "type": "OTHER",
      "metadata": {},
      "salience": 0.0031794568,
      "mentions": [
        {
          "text": {
            "content": "skin rashes",
            "beginOffset": -1
          },
          "type": "COMMON"
        }
      ]
    },
    {
      "name": "owner daughter",
      "type": "PERSON",
      "metadata": {},
      "salience": 0.0031674898,
      "mentions": [
        {
          "text": {
            "content": "owner daughter",
            "beginOffset": -1
          },
          "type": "COMMON"
        }
      ]
    },
    {
      "name": "medication",
      "type": "CONSUMER_GOOD",
      "metadata": {},
      "salience": 0.0027382614,
      "mentions": [
        {
          "text": {
            "content": "medication",
            "beginOffset": -1
          },
          "type": "COMMON"
        }
      ]
    },
    {
      "name": "home",
      "type": "LOCATION",
      "metadata": {},
      "salience": 0.0025563561,
      "mentions": [
        {
          "text": {
            "content": "home",
            "beginOffset": -1
          },
          "type": "COMMON"
        }
      ]
    },
    {
      "name": "loves",
      "type": "OTHER",
      "metadata": {},
      "salience": 0.0022455624,
      "mentions": [
        {
          "text": {
            "content": "loves",
            "beginOffset": -1
          },
          "type": "COMMON"
        }
      ]
    },
    {
      "name": "buddy",
      "type": "PERSON",
      "metadata": {},
      "salience": 0.0017879015,
      "mentions": [
        {
          "text": {
            "content": "buddy",
            "beginOffset": -1
          },
          "type": "COMMON"
        }
      ]
    },
    {
      "name": "foster sisters",
      "type": "PERSON",
      "metadata": {},
      "salience": 0.0017134403,
      "mentions": [
        {
          "text": {
            "content": "foster sisters",
            "beginOffset": -1
          },
          "type": "COMMON"
        }
      ]
    }
  ],
  "documentSentiment": {
    "magnitude": 4.3,
    "score": 0.3
  },
  "language": "en",
  "categories": []
}
