{
  "sentences": [
    {
      "text": {
        "content": "Pebby's a very loyal and playful puppy.",
        "beginOffset": -1
      },
      "sentiment": {
        "magnitude": 0.7,
        "score": 0.7
      }
    },
    {
      "text": {
        "content": "She loves cuddling and food.",
        "beginOffset": -1
      },
      "sentiment": {
        "magnitude": 0.9,
        "score": 0.9
      }
    }
  ],
  "tokens": [],
  "entities": [
    {
      "name": "Pebby",
      "type": "PERSON",
      "metadata": {},
      "salience": 0.7944215,
      "mentions": [
        {
          "text": {
            "content": "Pebby",
            "beginOffset": -1
          },
          "type": "PROPER"
        }
      ]
    },
    {
      "name": "puppy",
      "type": "OTHER",
      "metadata": {},
      "salience": 0.13542856,
      "mentions": [
        {
          "text": {
            "content": "puppy",
            "beginOffset": -1
          },
          "type": "COMMON"
        }
      ]
    },
    {
      "name": "food",
      "type": "OTHER",
      "metadata": {},
      "salience": 0.04760482,
      "mentions": [
        {
          "text": {
            "content": "food",
            "beginOffset": -1
          },
          "type": "COMMON"
        }
      ]
    },
    {
      "name": "cuddling",
      "type": "OTHER",
      "metadata": {},
      "salience": 0.022545101,
      "mentions": [
        {
          "text": {
            "content": "cuddling",
            "beginOffset": -1
          },
          "type": "COMMON"
        }
      ]
    }
  ],
  "documentSentiment": {
    "magnitude": 1.6,
    "score": 0.8
  },
  "language": "en",
  "categories": []
}
