{
  "sentences": [
    {
      "text": {
        "content": "I found this cat crying outside my house in the neighbour's yard, hiding under some bushes.",
        "beginOffset": -1
      },
      "sentiment": {
        "magnitude": 0.2,
        "score": 0.2
      }
    },
    {
      "text": {
        "content": "After I called the cat, he came running to me so there's a possibility he might have been owned before or he's used to people feeding him.",
        "beginOffset": -1
      },
      "sentiment": {
        "magnitude": 0.4,
        "score": 0.4
      }
    },
    {
      "text": {
        "content": "No collar, no microchip.",
        "beginOffset": -1
      },
      "sentiment": {
        "magnitude": 0.1,
        "score": -0.1
      }
    },
    {
      "text": {
        "content": "He's not shy at all and very responsive.",
        "beginOffset": -1
      },
      "sentiment": {
        "magnitude": 0.7,
        "score": 0.7
      }
    },
    {
      "text": {
        "content": "He has a wound on his leg and the vet said it's due to a fight he had with another tom cat.",
        "beginOffset": -1
      },
      "sentiment": {
        "magnitude": 0.4,
        "score": -0.4
      }
    },
    {
      "text": {
        "content": "The cat is at the vet and he'll be spayed.",
        "beginOffset": -1
      },
      "sentiment": {
        "magnitude": 0,
        "score": 0
      }
    },
    {
      "text": {
        "content": "He's not the neighbour's cat, I've already asked.",
        "beginOffset": -1
      },
      "sentiment": {
        "magnitude": 0,
        "score": 0
      }
    },
    {
      "text": {
        "content": "He is available for adoption by Friday (/) if no one claims him.",
        "beginOffset": -1
      },
      "sentiment": {
        "magnitude": 0,
        "score": 0
      }
    }
  ],
  "tokens": [],
  "entities": [
    {
      "name": "neighbour",
      "type": "PERSON",
      "metadata": {},
      "salience": 0.65704715,
      "mentions": [
        {
          "text": {
            "content": "neighbour",
            "beginOffset": -1
          },
          "type": "COMMON"
        }
      ]
    },
    {
      "name": "cat",
      "type": "OTHER",
      "metadata": {},
      "salience": 0.18904004,
      "mentions": [
        {
          "text": {
            "content": "cat",
            "beginOffset": -1
          },
          "type": "COMMON"
        },
        {
          "text": {
            "content": "cat",
            "beginOffset": -1
          },
          "type": "COMMON"
        }
      ]
    },
    {
      "name": "house",
      "type": "LOCATION",
      "metadata": {},
      "salience": 0.040181145,
      "mentions": [
        {
          "text": {
            "content": "house",
            "beginOffset": -1
          },
          "type": "COMMON"
        }
      ]
    },
    {
      "name": "yard",
      "type": "LOCATION",
      "metadata": {},
      "salience": 0.040181145,
      "mentions": [
        {
          "text": {
            "content": "yard",
            "beginOffset": -1
          },
          "type": "COMMON"
        }
      ]
    },
    {
      "name": "bushes",
      "type": "OTHER",
      "metadata": {},
      "salience": 0.015587807,
      "mentions": [
        {
          "text": {
            "content": "bushes",
            "beginOffset": -1
          },
          "type": "COMMON"
        }
      ]
    },
    {
      "name": "possibility",
      "type": "OTHER",
      "metadata": {},
      "salience": 0.0061207754,
      "mentions": [
        {
          "text": {
            "content": "possibility",
            "beginOffset": -1
          },
          "type": "COMMON"
        }
      ]
    },
    {
      "name": "collar",
      "type": "OTHER",
      "metadata": {},
      "salience": 0.0051308526,
      "mentions": [
        {
          "text": {
            "content": "collar",
            "beginOffset": -1
          },
          "type": "COMMON"
        }
      ]
    },
    {
      "name": "microchip",
      "type": "OTHER",
      "metadata": {},
      "salience": 0.0051308526,
      "mentions": [
        {
          "text": {
            "content": "microchip",
            "beginOffset": -1
          },
          "type": "COMMON"
        }
      ]
    },
    {
      "name": "people",
      "type": "PERSON",
      "metadata": {},
      "salience": 0.0050936113,
      "mentions": [
        {
          "text": {
            "content": "people",
            "beginOffset": -1
          },
          "type": "COMMON"
        }
      ]
    },
    {
      "name": "cat",
      "type": "OTHER",
      "metadata": {},
      "salience": 0.0049892836,
      "mentions": [
        {
          "text": {
            "content": "cat",
            "beginOffset": -1
          },
          "type": "COMMON"
        }
      ]
    },
    {
      "name": "vet",
      "type": "PERSON",
      "metadata": {},
      "salience": 0.004947555,
      "mentions": [
        {
          "text": {
            "content": "vet",
            "beginOffset": -1
          },
          "type": "COMMON"
        }
      ]
    },
    {
      "name": "leg",
      "type": "OTHER",
      "metadata": {},
      "salience": 0.0046796454,
      "mentions": [
        {
          "text": {
            "content": "leg",
            "beginOffset": -1
          },
          "type": "COMMON"
        }
      ]
    },
    {
      "name": "wound",
      "type": "OTHER",
      "metadata": {},
      "salience": 0.0046796454,
      "mentions": [
        {
          "text": {
            "content": "wound",
            "beginOffset": -1
          },
          "type": "COMMON"
        }
      ]
    },
    {
      "name": "neighbour",
      "type": "PERSON",
      "metadata": {},
      "salience": 0.0040001296,
      "mentions": [
        {
          "text": {
            "content": "neighbour",
            "beginOffset": -1
          },
          "type": "COMMON"
        }
      ]
    },
    {
      "name": "cat",
      "type": "OTHER",
      "metadata": {},
      "salience": 0.0026408255,
      "mentions": [
        {
          "text": {
            "content": "cat",
            "beginOffset": -1
          },
          "type": "COMMON"
        }
      ]
    },
    {
      "name": "no one",
      "type": "PERSON",
      "metadata": {},
      "salience": 0.0025814339,
      "mentions": [
        {
          "text": {
            "content": "no one",
            "beginOffset": -1
          },
          "type": "COMMON"
        }
      ]
    },
    {
      "name": "adoption",
      "type": "OTHER",
      "metadata": {},
      "salience": 0.002457639,
      "mentions": [
        {
          "text": {
            "content": "adoption",
            "beginOffset": -1
          },
          "type": "COMMON"
        }
      ]
    },
    {
      "name": "tom cat",
      "type": "PERSON",
      "metadata": {},
      "salience": 0.0022012433,
      "mentions": [
        {
          "text": {
            "content": "tom cat",
            "beginOffset": -1
          },
          "type": "COMMON"
        }
      ]
    },
    {
      "name": "vet",
      "type": "PERSON",
      "metadata": {},
      "salience": 0.0017598699,
      "mentions": [
        {
          "text": {
            "content": "vet",
            "beginOffset": -1
          },
          "type": "COMMON"
        }
      ]
    },
    {
      "name": "fight",
      "type": "EVENT",
      "metadata": {},
      "salience": 0.0015493657,
      "mentions": [
        {
          "text": {
            "content": "fight",
            "beginOffset": -1
          },
          "type": "COMMON"
        }
      ]
    }
  ],
  "documentSentiment": {
    "magnitude": 2,
    "score": 0.1
  },
  "language": "en",
  "categories": []
}
