{
  "sentences": [
    {
      "text": {
        "content": "Ashley, Jessica and Jay were brought to our attention a few weeks ago and Ashley has been adopted and now so has Jessica!",
        "beginOffset": -1
      },
      "sentiment": {
        "magnitude": 0.2,
        "score": 0.2
      }
    },
    {
      "text": {
        "content": "Today info in that Jay is being returned so sad.",
        "beginOffset": -1
      },
      "sentiment": {
        "magnitude": 0.1,
        "score": -0.1
      }
    },
    {
      "text": {
        "content": "3/4/ posting - The black male puppy, Jay is coming back this week.",
        "beginOffset": -1
      },
      "sentiment": {
        "magnitude": 0,
        "score": 0
      }
    },
    {
      "text": {
        "content": "So he is for adoption.",
        "beginOffset": -1
      },
      "sentiment": {
        "magnitude": 0,
        "score": 0
      }
    },
    {
      "text": {
        "content": "The neighbours complain when he barks and they play...",
        "beginOffset": -1
      },
      "sentiment": {
        "magnitude": 0.3,
        "score": -0.3
      }
    },
    {
      "text": {
        "content": "What a cop out...",
        "beginOffset": -1
      },
      "sentiment": {
        "magnitude": 0,
        "score": 0
      }
    },
    {
      "text": {
        "content": "A dog is a commitment through good times and bad, through human babies births and times sad Through difficulties, adjustments and not just the glad A dog is for life or else it's too bad...",
        "beginOffset": -1
      },
      "sentiment": {
        "magnitude": 0.4,
        "score": -0.4
      }
    },
    {
      "text": {
        "content": "And very sad A dog will be the source of the most love you've ever had A dog will never leave you When times become bad..",
        "beginOffset": -1
      },
      "sentiment": {
        "magnitude": 0.7,
        "score": 0.7
      }
    },
    {
      "text": {
        "content": "30.3.",
        "beginOffset": -1
      },
      "sentiment": {
        "magnitude": 0.1,
        "score": 0.1
      }
    },
    {
      "text": {
        "content": "- Jessica is potentially adopted they are fetching her on the 1st April, keeping this going just in case, she is shy and loves being hugged and carried.",
        "beginOffset": -1
      },
      "sentiment": {
        "magnitude": 0.4,
        "score": 0.4
      }
    },
    {
      "text": {
        "content": "Please adopt her shes so sweet...",
        "beginOffset": -1
      },
      "sentiment": {
        "magnitude": 0.4,
        "score": 0.4
      }
    }
  ],
  "tokens": [],
  "entities": [
    {
      "name": "Jessica",
      "type": "PERSON",
      "metadata": {},
      "salience": 0.32702044,
      "mentions": [
        {
          "text": {
            "content": "Jessica",
            "beginOffset": -1
          },
          "type": "PROPER"
        },
        {
          "text": {
            "content": "Jessica",
            "beginOffset": -1
          },
          "type": "PROPER"
        },
        {
          "text": {
            "content": "Jessica",
            "beginOffset": -1
          },
          "type": "PROPER"
        }
      ]
    },
    {
      "name": "Jay",
      "type": "PERSON",
      "metadata": {},
      "salience": 0.29331967,
      "mentions": [
        {
          "text": {
            "content": "Jay",
            "beginOffset": -1
          },
          "type": "PROPER"
        },
        {
          "text": {
            "content": "Jay",
            "beginOffset": -1
          },
          "type": "PROPER"
        },
        {
          "text": {
            "content": "Jay",
            "beginOffset": -1
          },
          "type": "PROPER"
        }
      ]
    },
    {
      "name": "Ashley",
      "type": "PERSON",
      "metadata": {},
      "salience": 0.075372726,
      "mentions": [
        {
          "text": {
            "content": "Ashley",
            "beginOffset": -1
          },
          "type": "PROPER"
        },
        {
          "text": {
            "content": "Ashley",
            "beginOffset": -1
          },
          "type": "PROPER"
        }
      ]
    },
    {
      "name": "attention",
      "type": "OTHER",
      "metadata": {},
      "salience": 0.05764956,
      "mentions": [
        {
          "text": {
            "content": "attention",
            "beginOffset": -1
          },
          "type": "COMMON"
        }
      ]
    },
    {
      "name": "commitment",
      "type": "OTHER",
      "metadata": {},
      "salience": 0.049535513,
      "mentions": [
        {
          "text": {
            "content": "dog",
            "beginOffset": -1
          },
          "type": "COMMON"
        },
        {
          "text": {
            "content": "commitment",
            "beginOffset": -1
          },
          "type": "COMMON"
        }
      ]
    },
    {
      "name": "times",
      "type": "OTHER",
      "metadata": {},
      "salience": 0.041493002,
      "mentions": [
        {
          "text": {
            "content": "times",
            "beginOffset": -1
          },
          "type": "COMMON"
        },
        {
          "text": {
            "content": "times",
            "beginOffset": -1
          },
          "type": "COMMON"
        }
      ]
    },
    {
      "name": "info",
      "type": "OTHER",
      "metadata": {},
      "salience": 0.027220853,
      "mentions": [
        {
          "text": {
            "content": "info",
            "beginOffset": -1
          },
          "type": "COMMON"
        }
      ]
    },
    {
      "name": "neighbours",
      "type": "PERSON",
      "metadata": {},
      "salience": 0.017595675,
      "mentions": [
        {
          "text": {
            "content": "neighbours",
            "beginOffset": -1
          },
          "type": "COMMON"
        }
      ]
    },
    {
      "name": "source",
      "type": "OTHER",
      "metadata": {},
      "salience": 0.015116512,
      "mentions": [
        {
          "text": {
            "content": "A dog",
            "beginOffset": -1
          },
          "type": "COMMON"
        },
        {
          "text": {
            "content": "source",
            "beginOffset": -1
          },
          "type": "COMMON"
        }
      ]
    },
    {
      "name": "posting",
      "type": "OTHER",
      "metadata": {},
      "salience": 0.010706804,
      "mentions": [
        {
          "text": {
            "content": "posting",
            "beginOffset": -1
          },
          "type": "COMMON"
        }
      ]
    },
    {
      "name": "puppy",
      "type": "OTHER",
      "metadata": {},
      "salience": 0.010706804,
      "mentions": [
        {
          "text": {
            "content": "puppy",
            "beginOffset": -1
          },
          "type": "COMMON"
        }
      ]
    },
    {
      "name": "dog",
      "type": "OTHER",
      "metadata": {},
      "salience": 0.010703694,
      "mentions": [
        {
          "text": {
            "content": "dog",
            "beginOffset": -1
          },
          "type": "COMMON"
        }
      ]
    },
    {
      "name": "cop",
      "type": "PERSON",
      "metadata": {},
      "salience": 0.0072619007,
      "mentions": [
        {
          "text": {
            "content": "cop",
            "beginOffset": -1
          },
          "type": "COMMON"
        }
      ]
    },
    {
      "name": "births",
      "type": "EVENT",
      "metadata": {},
      "salience": 0.007248187,
      "mentions": [
        {
          "text": {
            "content": "births",
            "beginOffset": -1
          },
          "type": "COMMON"
        }
      ]
    },
    {
      "name": "human babies",
      "type": "PERSON",
      "metadata": {},
      "salience": 0.007248187,
      "mentions": [
        {
          "text": {
            "content": "human babies",
            "beginOffset": -1
          },
          "type": "COMMON"
        }
      ]
    },
    {
      "name": "adoption",
      "type": "OTHER",
      "metadata": {},
      "salience": 0.0072091506,
      "mentions": [
        {
          "text": {
            "content": "adoption",
            "beginOffset": -1
          },
          "type": "COMMON"
        }
      ]
    },
    {
      "name": "difficulties",
      "type": "OTHER",
      "metadata": {},
      "salience": 0.0066518723,
      "mentions": [
        {
          "text": {
            "content": "difficulties",
            "beginOffset": -1
          },
          "type": "COMMON"
        }
      ]
    },
    {
      "name": "adjustments",
      "type": "OTHER",
      "metadata": {},
      "salience": 0.0066518723,
      "mentions": [
        {
          "text": {
            "content": "adjustments",
            "beginOffset": -1
          },
          "type": "COMMON"
        }
      ]
    },
    {
      "name": "life",
      "type": "OTHER",
      "metadata": {},
      "salience": 0.0066518723,
      "mentions": [
        {
          "text": {
            "content": "life",
            "beginOffset": -1
          },
          "type": "COMMON"
        }
      ]
    },
    {
      "name": "case",
      "type": "OTHER",
      "metadata": {},
      "salience": 0.0034971158,
      "mentions": [
        {
          "text": {
            "content": "case",
            "beginOffset": -1
          },
          "type": "COMMON"
        }
      ]
    },
    {
      "name": "shes",
      "type": "OTHER",
      "metadata": {},
      "salience": 0.0034930212,
      "mentions": [
        {
          "text": {
            "content": "shes",
            "beginOffset": -1
          },
          "type": "COMMON"
        }
      ]
    },
    {
      "name": "dog",
      "type": "OTHER",
      "metadata": {},
      "salience": 0.002945873,
      "mentions": [
        {
          "text": {
            "content": "dog",
            "beginOffset": -1
          },
          "type": "COMMON"
        }
      ]
    },
    {
      "name": "love",
      "type": "OTHER",
      "metadata": {},
      "salience": 0.0025019746,
      "mentions": [
        {
          "text": {
            "content": "love",
            "beginOffset": -1
          },
          "type": "COMMON"
        }
      ]
    },
    {
      "name": "most",
      "type": "LOCATION",
      "metadata": {},
      "salience": 0.0021977013,
      "mentions": [
        {
          "text": {
            "content": "most",
            "beginOffset": -1
          },
          "type": "COMMON"
        }
      ]
    }
  ],
  "documentSentiment": {
    "magnitude": 3.1,
    "score": 0.1
  },
  "language": "en",
  "categories": []
}
