{
  "sentences": [
    {
      "text": {
        "content": "This fur kid was rescued from the back lane of my office this afternoon.",
        "beginOffset": -1
      },
      "sentiment": {
        "magnitude": 0,
        "score": 0
      }
    },
    {
      "text": {
        "content": "He was screaming so loud that he caught my attention.",
        "beginOffset": -1
      },
      "sentiment": {
        "magnitude": 0.1,
        "score": -0.1
      }
    },
    {
      "text": {
        "content": "I was that time on the first floor of my office.",
        "beginOffset": -1
      },
      "sentiment": {
        "magnitude": 0,
        "score": 0
      }
    },
    {
      "text": {
        "content": "Immediately I went down and saw him alone at a corner.",
        "beginOffset": -1
      },
      "sentiment": {
        "magnitude": 0.2,
        "score": -0.2
      }
    },
    {
      "text": {
        "content": "He was so terrified that he peed.",
        "beginOffset": -1
      },
      "sentiment": {
        "magnitude": 0.3,
        "score": 0.3
      }
    },
    {
      "text": {
        "content": "I had then took him to the vet for medical check and treatment.",
        "beginOffset": -1
      },
      "sentiment": {
        "magnitude": 0,
        "score": 0
      }
    },
    {
      "text": {
        "content": "He is fine and he is 0.5kg.",
        "beginOffset": -1
      },
      "sentiment": {
        "magnitude": 0.1,
        "score": 0.1
      }
    },
    {
      "text": {
        "content": "Please adopt this cute little furry kid and let him have a better life, and not being a stray cat.",
        "beginOffset": -1
      },
      "sentiment": {
        "magnitude": 0,
        "score": 0
      }
    },
    {
      "text": {
        "content": "Let us together control the population and misery of strays.",
        "beginOffset": -1
      },
      "sentiment": {
        "magnitude": 0.5,
        "score": -0.5
      }
    },
    {
      "text": {
        "content": "Thank you.",
        "beginOffset": -1
      },
      "sentiment": {
        "magnitude": 0,
        "score": 0
      }
    }
  ],
  "tokens": [],
  "entities": [
    {
      "name": "fur kid",
      "type": "PERSON",
      "metadata": {},
      "salience": 0.47859502,
      "mentions": [
        {
          "text": {
            "content": "fur kid",
            "beginOffset": -1
          },
          "type": "COMMON"
        }
      ]
    },
    {
      "name": "office",
      "type": "OTHER",
      "metadata": {},
      "salience": 0.26636598,
      "mentions": [
        {
          "text": {
            "content": "office",
            "beginOffset": -1
          },
          "type": "COMMON"
        },
        {
          "text": {
            "content": "office",
            "beginOffset": -1
          },
          "type": "COMMON"
        }
      ]
    },
    {
      "name": "lane",
      "type": "LOCATION",
      "metadata": {},
      "salience": 0.1023369,
      "mentions": [
        {
          "text": {
            "content": "lane",
            "beginOffset": -1
          },
          "type": "COMMON"
        }
      ]
    },
    {
      "name": "kid",
      "type": "PERSON",
      "metadata": {},
      "salience": 0.03439514,
      "mentions": [
        {
          "text": {
            "content": "kid",
            "beginOffset": -1
          },
          "type": "COMMON"
        }
      ]
    },
    {
      "name": "attention",
      "type": "OTHER",
      "metadata": {},
      "salience": 0.019341351,
      "mentions": [
        {
          "text": {
            "content": "attention",
            "beginOffset": -1
          },
          "type": "COMMON"
        }
      ]
    },
    {
      "name": "corner",
      "type": "LOCATION",
      "metadata": {},
      "salience": 0.013130644,
      "mentions": [
        {
          "text": {
            "content": "corner",
            "beginOffset": -1
          },
          "type": "COMMON"
        }
      ]
    },
    {
      "name": "floor",
      "type": "LOCATION",
      "metadata": {},
      "salience": 0.013016676,
      "mentions": [
        {
          "text": {
            "content": "floor",
            "beginOffset": -1
          },
          "type": "COMMON"
        }
      ]
    },
    {
      "name": "vet",
      "type": "PERSON",
      "metadata": {},
      "salience": 0.011992663,
      "mentions": [
        {
          "text": {
            "content": "vet",
            "beginOffset": -1
          },
          "type": "COMMON"
        }
      ]
    },
    {
      "name": "check",
      "type": "OTHER",
      "metadata": {},
      "salience": 0.011992663,
      "mentions": [
        {
          "text": {
            "content": "check",
            "beginOffset": -1
          },
          "type": "COMMON"
        }
      ]
    },
    {
      "name": "treatment",
      "type": "OTHER",
      "metadata": {},
      "salience": 0.011992663,
      "mentions": [
        {
          "text": {
            "content": "treatment",
            "beginOffset": -1
          },
          "type": "COMMON"
        }
      ]
    },
    {
      "name": "cat",
      "type": "OTHER",
      "metadata": {},
      "salience": 0.009015257,
      "mentions": [
        {
          "text": {
            "content": "cat",
            "beginOffset": -1
          },
          "type": "COMMON"
        }
      ]
    },
    {
      "name": "life",
      "type": "OTHER",
      "metadata": {},
      "salience": 0.008905374,
      "mentions": [
        {
          "text": {
            "content": "life",
            "beginOffset": -1
          },
          "type": "COMMON"
        }
      ]
    },
    {
      "name": "population",
      "type": "PERSON",
      "metadata": {},
      "salience": 0.006306559,
      "mentions": [
        {
          "text": {
            "content": "population",
            "beginOffset": -1
          },
          "type": "COMMON"
        }
      ]
    },
    {
      "name": "misery",
      "type": "OTHER",
      "metadata": {},
      "salience": 0.006306559,
      "mentions": [
        {
          "text": {
            "content": "misery",
            "beginOffset": -1
          },
          "type": "COMMON"
        }
      ]
    },
    {
      "name": "strays",
      "type": "OTHER",
      "metadata": {},
      "salience": 0.006306559,
      "mentions": [
        {
          "text": {
            "content": "strays",
            "beginOffset": -1
          },
          "type": "COMMON"
        }
      ]
    }
  ],
  "documentSentiment": {
    "magnitude": 1.6,
    "score": 0
  },
  "language": "en",
  "categories": []
}
