{
  "sentences": [
    {
      "text": {
        "content": "Small, black fur little girl.",
        "beginOffset": -1
      },
      "sentiment": {
        "magnitude": 0,
        "score": 0
      }
    },
    {
      "text": {
        "content": "Rescued at 1 week old, has now grown up into 1 month old kitten.",
        "beginOffset": -1
      },
      "sentiment": {
        "magnitude": 0,
        "score": 0
      }
    },
    {
      "text": {
        "content": "Dewormed and soon to be vaccinated (too young).",
        "beginOffset": -1
      },
      "sentiment": {
        "magnitude": 0,
        "score": 0
      }
    },
    {
      "text": {
        "content": "Has started eating soft solid foods &amp; kibble, also has been given ongoing practice of using sandbox for toilet use.",
        "beginOffset": -1
      },
      "sentiment": {
        "magnitude": 0.4,
        "score": 0.4
      }
    },
    {
      "text": {
        "content": "Fidget, is very mild mannered and easy to care for.",
        "beginOffset": -1
      },
      "sentiment": {
        "magnitude": 0.9,
        "score": 0.9
      }
    },
    {
      "text": {
        "content": "Playful and gentle, great for kids and young couples looking for their first pet.",
        "beginOffset": -1
      },
      "sentiment": {
        "magnitude": 0.9,
        "score": 0.9
      }
    },
    {
      "text": {
        "content": "Would love to have her go to a loving family who can give her care and attention.",
        "beginOffset": -1
      },
      "sentiment": {
        "magnitude": 0.8,
        "score": 0.8
      }
    }
  ],
  "tokens": [],
  "entities": [
    {
      "name": "girl",
      "type": "PERSON",
      "metadata": {},
      "salience": 0.24515203,
      "mentions": [
        {
          "text": {
            "content": "girl",
            "beginOffset": -1
          },
          "type": "COMMON"
        }
      ]
    },
    {
      "name": "fur",
      "type": "OTHER",
      "metadata": {},
      "salience": 0.24515203,
      "mentions": [
        {
          "text": {
            "content": "fur",
            "beginOffset": -1
          },
          "type": "COMMON"
        }
      ]
    },
    {
      "name": "family",
      "type": "PERSON",
      "metadata": {},
      "salience": 0.110693075,
      "mentions": [
        {
          "text": {
            "content": "family",
            "beginOffset": -1
          },
          "type": "COMMON"
        }
      ]
    },
    {
      "name": "kids",
      "type": "PERSON",
      "metadata": {},
      "salience": 0.07731109,
      "mentions": [
        {
          "text": {
            "content": "kids",
            "beginOffset": -1
          },
          "type": "COMMON"
        }
      ]
    },
    {
      "name": "kitten",
      "type": "PERSON",
      "metadata": {},
      "salience": 0.047669254,
      "mentions": [
        {
          "text": {
            "content": "kitten",
            "beginOffset": -1
          },
          "type": "COMMON"
        }
      ]
    },
    {
      "name": "sandbox",
      "type": "OTHER",
      "metadata": {},
      "salience": 0.03282964,
      "mentions": [
        {
          "text": {
            "content": "sandbox",
            "beginOffset": -1
          },
          "type": "COMMON"
        }
      ]
    },
    {
      "name": "foods",
      "type": "OTHER",
      "metadata": {},
      "salience": 0.03243216,
      "mentions": [
        {
          "text": {
            "content": "foods",
            "beginOffset": -1
          },
          "type": "COMMON"
        }
      ]
    },
    {
      "name": "kibble",
      "type": "OTHER",
      "metadata": {},
      "salience": 0.03243216,
      "mentions": [
        {
          "text": {
            "content": "kibble",
            "beginOffset": -1
          },
          "type": "COMMON"
        }
      ]
    },
    {
      "name": "toilet use",
      "type": "OTHER",
      "metadata": {},
      "salience": 0.029780004,
      "mentions": [
        {
          "text": {
            "content": "toilet use",
            "beginOffset": -1
          },
          "type": "COMMON"
        }
      ]
    },
    {
      "name": "Dewormed",
      "type": "OTHER",
      "metadata": {
        "wikipedia_url": "https://en.wikipedia.org/wiki/Deworming",
        "mid": "/m/03nnncz"
      },
      "salience": 0.0282071,
      "mentions": [
        {
          "text": {
            "content": "Dewormed",
            "beginOffset": -1
          },
          "type": "PROPER"
        }
      ]
    },
    {
      "name": "practice",
      "type": "OTHER",
      "metadata": {},
      "salience": 0.024798395,
      "mentions": [
        {
          "text": {
            "content": "practice",
            "beginOffset": -1
          },
          "type": "COMMON"
        }
      ]
    },
    {
      "name": "couples",
      "type": "PERSON",
      "metadata": {},
      "salience": 0.022377837,
      "mentions": [
        {
          "text": {
            "content": "couples",
            "beginOffset": -1
          },
          "type": "COMMON"
        }
      ]
    },
    {
      "name": "pet",
      "type": "OTHER",
      "metadata": {},
      "salience": 0.022377837,
      "mentions": [
        {
          "text": {
            "content": "pet",
            "beginOffset": -1
          },
          "type": "COMMON"
        }
      ]
    },
    {
      "name": "Fidget",
      "type": "OTHER",
      "metadata": {
        "mid": "/m/04y6tl1",
        "wikipedia_url": "https://en.wikipedia.org/wiki/Fidgeting"
      },
      "salience": 0.021165757,
      "mentions": [
        {
          "text": {
            "content": "Fidget",
            "beginOffset": -1
          },
          "type": "PROPER"
        }
      ]
    },
    {
      "name": "attention",
      "type": "OTHER",
      "metadata": {},
      "salience": 0.015662204,
      "mentions": [
        {
          "text": {
            "content": "attention",
            "beginOffset": -1
          },
          "type": "COMMON"
        }
      ]
    },
    {
      "name": "care",
      "type": "OTHER",
      "metadata": {},
      "salience": 0.011959429,
      "mentions": [
        {
          "text": {
            "content": "care",
            "beginOffset": -1
          },
          "type": "COMMON"
        }
      ]
    }
  ],
  "documentSentiment": {
    "magnitude": 3.2,
    "score": 0.4
  },
  "language": "en",
  "categories": []
}
