{
  "sentences": [
    {
      "text": {
        "content": "Clara is a very steady, calm dog.",
        "beginOffset": -1
      },
      "sentiment": {
        "magnitude": 0.9,
        "score": 0.9
      }
    },
    {
      "text": {
        "content": "She was found in Damansara Kim but we couldn't track her owner after weeks.",
        "beginOffset": -1
      },
      "sentiment": {
        "magnitude": 0.2,
        "score": -0.2
      }
    },
    {
      "text": {
        "content": "Hence would like to find her a good home.",
        "beginOffset": -1
      },
      "sentiment": {
        "magnitude": 0.7,
        "score": 0.7
      }
    },
    {
      "text": {
        "content": "She makes a wonderful companion and great for first time dog owners.",
        "beginOffset": -1
      },
      "sentiment": {
        "magnitude": 0.9,
        "score": 0.9
      }
    },
    {
      "text": {
        "content": "Vaccination and neutering cost to be borne by adopter.",
        "beginOffset": -1
      },
      "sentiment": {
        "magnitude": 0.7,
        "score": 0.7
      }
    },
    {
      "text": {
        "content": "Please call if u can give her a good home.",
        "beginOffset": -1
      },
      "sentiment": {
        "magnitude": 0.3,
        "score": 0.3
      }
    }
  ],
  "tokens": [],
  "entities": [
    {
      "name": "Clara",
      "type": "PERSON",
      "metadata": {},
      "salience": 0.707855,
      "mentions": [
        {
          "text": {
            "content": "Clara",
            "beginOffset": -1
          },
          "type": "PROPER"
        }
      ]
    },
    {
      "name": "dog",
      "type": "OTHER",
      "metadata": {},
      "salience": 0.18374716,
      "mentions": [
        {
          "text": {
            "content": "dog",
            "beginOffset": -1
          },
          "type": "COMMON"
        }
      ]
    },
    {
      "name": "home",
      "type": "LOCATION",
      "metadata": {},
      "salience": 0.030928953,
      "mentions": [
        {
          "text": {
            "content": "home",
            "beginOffset": -1
          },
          "type": "COMMON"
        }
      ]
    },
    {
      "name": "owner",
      "type": "PERSON",
      "metadata": {},
      "salience": 0.019862613,
      "mentions": [
        {
          "text": {
            "content": "owner",
            "beginOffset": -1
          },
          "type": "COMMON"
        }
      ]
    },
    {
      "name": "Damansara Kim",
      "type": "LOCATION",
      "metadata": {
        "mid": "/g/1q5bnbb60"
      },
      "salience": 0.015332102,
      "mentions": [
        {
          "text": {
            "content": "Damansara Kim",
            "beginOffset": -1
          },
          "type": "PROPER"
        }
      ]
    },
    {
      "name": "companion",
      "type": "OTHER",
      "metadata": {},
      "salience": 0.012775514,
      "mentions": [
        {
          "text": {
            "content": "companion",
            "beginOffset": -1
          },
          "type": "COMMON"
        }
      ]
    },
    {
      "name": "home",
      "type": "LOCATION",
      "metadata": {},
      "salience": 0.007379603,
      "mentions": [
        {
          "text": {
            "content": "home",
            "beginOffset": -1
          },
          "type": "COMMON"
        }
      ]
    },
    {
      "name": "dog owners",
      "type": "PERSON",
      "metadata": {},
      "salience": 0.006095386,
      "mentions": [
        {
          "text": {
            "content": "dog owners",
            "beginOffset": -1
          },
          "type": "COMMON"
        }
      ]
    },
    {
      "name": "cost",
      "type": "OTHER",
      "metadata": {},
      "salience": 0.005341237,
      "mentions": [
        {
          "text": {
            "content": "cost",
            "beginOffset": -1
          },
          "type": "COMMON"
        }
      ]
    },
    {
      "name": "Vaccination",
      "type": "OTHER",
      "metadata": {},
      "salience": 0.005341237,
      "mentions": [
        {
          "text": {
            "content": "Vaccination",
            "beginOffset": -1
          },
          "type": "COMMON"
        }
      ]
    },
    {
      "name": "neutering",
      "type": "OTHER",
      "metadata": {},
      "salience": 0.005341237,
      "mentions": [
        {
          "text": {
            "content": "neutering",
            "beginOffset": -1
          },
          "type": "COMMON"
        }
      ]
    }
  ],
  "documentSentiment": {
    "magnitude": 3.9,
    "score": 0.5
  },
  "language": "en",
  "categories": []
}
