{
  "sentences": [
    {
      "text": {
        "content": "I have been feeding this pretty girl for almost 2 years.",
        "beginOffset": -1
      },
      "sentiment": {
        "magnitude": 0.3,
        "score": 0.3
      }
    },
    {
      "text": {
        "content": "Finally got the chance to gain her trust and bring her home to temporarily foster her.",
        "beginOffset": -1
      },
      "sentiment": {
        "magnitude": 0.2,
        "score": 0.2
      }
    },
    {
      "text": {
        "content": "Her temperament is super friendly with humans and absolutely loves to give affection.",
        "beginOffset": -1
      },
      "sentiment": {
        "magnitude": 0.9,
        "score": 0.9
      }
    },
    {
      "text": {
        "content": "Character similar to a Labrador.",
        "beginOffset": -1
      },
      "sentiment": {
        "magnitude": 0.4,
        "score": 0.4
      }
    },
    {
      "text": {
        "content": "I will be neutering her before she gets adopted.",
        "beginOffset": -1
      },
      "sentiment": {
        "magnitude": 0,
        "score": 0
      }
    }
  ],
  "tokens": [],
  "entities": [
    {
      "name": "girl",
      "type": "PERSON",
      "metadata": {},
      "salience": 0.8313957,
      "mentions": [
        {
          "text": {
            "content": "girl",
            "beginOffset": -1
          },
          "type": "COMMON"
        }
      ]
    },
    {
      "name": "temperament",
      "type": "OTHER",
      "metadata": {},
      "salience": 0.034068722,
      "mentions": [
        {
          "text": {
            "content": "temperament",
            "beginOffset": -1
          },
          "type": "COMMON"
        }
      ]
    },
    {
      "name": "trust",
      "type": "OTHER",
      "metadata": {},
      "salience": 0.03069089,
      "mentions": [
        {
          "text": {
            "content": "trust",
            "beginOffset": -1
          },
          "type": "COMMON"
        }
      ]
    },
    {
      "name": "humans",
      "type": "PERSON",
      "metadata": {},
      "salience": 0.028390428,
      "mentions": [
        {
          "text": {
            "content": "humans",
            "beginOffset": -1
          },
          "type": "COMMON"
        }
      ]
    },
    {
      "name": "home",
      "type": "LOCATION",
      "metadata": {},
      "salience": 0.02684608,
      "mentions": [
        {
          "text": {
            "content": "home",
            "beginOffset": -1
          },
          "type": "COMMON"
        }
      ]
    },
    {
      "name": "chance",
      "type": "OTHER",
      "metadata": {},
      "salience": 0.019312685,
      "mentions": [
        {
          "text": {
            "content": "chance",
            "beginOffset": -1
          },
          "type": "COMMON"
        }
      ]
    },
    {
      "name": "Labrador",
      "type": "LOCATION",
      "metadata": {
        "mid": "/m/0km3f",
        "wikipedia_url": "https://en.wikipedia.org/wiki/Labrador_Retriever"
      },
      "salience": 0.012673202,
      "mentions": [
        {
          "text": {
            "content": "Labrador",
            "beginOffset": -1
          },
          "type": "PROPER"
        }
      ]
    },
    {
      "name": "Character",
      "type": "OTHER",
      "metadata": {},
      "salience": 0.009412182,
      "mentions": [
        {
          "text": {
            "content": "Character",
            "beginOffset": -1
          },
          "type": "COMMON"
        }
      ]
    },
    {
      "name": "affection",
      "type": "OTHER",
      "metadata": {},
      "salience": 0.007210144,
      "mentions": [
        {
          "text": {
            "content": "affection",
            "beginOffset": -1
          },
          "type": "COMMON"
        }
      ]
    }
  ],
  "documentSentiment": {
    "magnitude": 2.1,
    "score": 0.4
  },
  "language": "en",
  "categories": []
}
